pomody/__init__.py
pomody/__main__.py
pomody/console.py
pomody/pomody.py
pomody-0.5.2.dist-info/METADATA
pomody-0.5.2.dist-info/WHEEL
pomody-0.5.2.dist-info/entry_points.txt
pomody-0.5.2.dist-info/top_level.txt
pomody-0.5.2.dist-info/RECORD
