Metadata-Version: 2.1
Name: pomody
Version: 0.5.2
Summary: A pomodoro CLI app
Home-page: https://github.com/Tekofx/pomody
Download-URL: https://github.com/Tekofx/pomody/archive/refs/tags/
Author: Teko
Author-email: tekofxx@gmail.com
License: MIT
Keywords: pomodoro,productivity,time,timer,work
Platform: UNKNOWN
Classifier: Development Status :: 4 - Beta
Classifier: Intended Audience :: Developers
Classifier: Topic :: Software Development :: Build Tools
Classifier: License :: OSI Approved :: MIT License
Classifier: Programming Language :: Python :: 3
Classifier: Programming Language :: Python :: 3.4
Classifier: Programming Language :: Python :: 3.5
Classifier: Programming Language :: Python :: 3.6
Classifier: Programming Language :: Python :: 3.8
Requires-Dist: rich
Requires-Dist: plyer
